acestream/__init__.py
acestream/engine.py
acestream/object.py
acestream/search.py
acestream/server.py
acestream/stream.py
acestream-0.2.0.dist-info/LICENSE.txt
acestream-0.2.0.dist-info/METADATA
acestream-0.2.0.dist-info/WHEEL
acestream-0.2.0.dist-info/top_level.txt
acestream-0.2.0.dist-info/RECORD
