Metadata-Version: 2.1
Name: acestream
Version: 0.2.0
Summary: Interact with the AceStream Engine and the HTTP API
Home-page: https://github.com/jonian/python-acestream
Author: Jonian Guveli
Author-email: jonian@hardpixel.eu
License: UNKNOWN
Project-URL: Bug Reports, https://github.com/jonian/python-acestream/issues
Project-URL: Source, https://github.com/jonian/python-acestream
Platform: UNKNOWN
Classifier: Programming Language :: Python :: 2
Classifier: Programming Language :: Python :: 3
Classifier: License :: OSI Approved :: GNU General Public License v3 (GPLv3)
Classifier: Operating System :: POSIX :: Linux
